ParallelPipe/Buffer.py
ParallelPipe/Pipeline.py
ParallelPipe/Stage.py
ParallelPipe/__init__.py
PyParallelPipe-1.0.2.dist-info/LICENSE
PyParallelPipe-1.0.2.dist-info/METADATA
PyParallelPipe-1.0.2.dist-info/WHEEL
PyParallelPipe-1.0.2.dist-info/top_level.txt
PyParallelPipe-1.0.2.dist-info/RECORD
