Metadata-Version: 2.1
Name: PyParallelPipe
Version: 1.0.2
Summary: Using this ParallelPipe library, it is very fast and easy to build parallel acceleration for multi-stage tasks, including deep learning. This code library does not require any dependencies and consists of pure Python code.
Home-page: https://github.com/gongpx20069/ParallelPipe
Author: PayShown
Author-email: pxgong19@fudan.edu.cn
Classifier: Programming Language :: Python :: 3
Classifier: License :: OSI Approved :: MIT License
Classifier: Operating System :: OS Independent
Requires-Python: >=3
License-File: LICENSE
